curlylint/__init__.py
curlylint/__main__.py
curlylint/ast.py
curlylint/check.py
curlylint/check_node.py
curlylint/cli.py
curlylint/cli_test.py
curlylint/config.py
curlylint/file.py
curlylint/issue.py
curlylint/issue_test.py
curlylint/lint.py
curlylint/parse.py
curlylint/parse_test.py
curlylint/py.typed
curlylint/report.py
curlylint/rule_param.py
curlylint/template_tags_param.py
curlylint/util.py
curlylint/util_test.py
curlylint/formatters/__init__.py
curlylint/formatters/compact.py
curlylint/formatters/json.py
curlylint/formatters/stylish.py
curlylint/rules/__init__.py
curlylint/rules/rule_test_case.py
curlylint/rules/aria_role/__init__.py
curlylint/rules/aria_role/aria_role.py
curlylint/rules/aria_role/aria_role_test.json
curlylint/rules/aria_role/aria_role_test.py
curlylint/rules/django_forms_rendering/__init__.py
curlylint/rules/django_forms_rendering/django_forms_rendering.py
curlylint/rules/django_forms_rendering/django_forms_rendering_test.json
curlylint/rules/django_forms_rendering/django_forms_rendering_test.py
curlylint/rules/html_has_lang/__init__.py
curlylint/rules/html_has_lang/html_has_lang.py
curlylint/rules/html_has_lang/html_has_lang_test.json
curlylint/rules/html_has_lang/html_has_lang_test.py
curlylint/rules/image_alt/__init__.py
curlylint/rules/image_alt/image_alt.py
curlylint/rules/image_alt/image_alt_test.json
curlylint/rules/image_alt/image_alt_test.py
curlylint/rules/indent/__init__.py
curlylint/rules/indent/indent.py
curlylint/rules/indent/indent_test.json
curlylint/rules/meta_viewport/__init__.py
curlylint/rules/meta_viewport/meta_viewport.py
curlylint/rules/meta_viewport/meta_viewport_test.json
curlylint/rules/meta_viewport/meta_viewport_test.py
curlylint/rules/no_autofocus/__init__.py
curlylint/rules/no_autofocus/no_autofocus.py
curlylint/rules/no_autofocus/no_autofocus_test.json
curlylint/rules/no_autofocus/no_autofocus_test.py
curlylint/rules/tabindex_no_positive/__init__.py
curlylint/rules/tabindex_no_positive/tabindex_no_positive.py
curlylint-0.13.0.dist-info/LICENSE
curlylint-0.13.0.dist-info/METADATA
curlylint-0.13.0.dist-info/WHEEL
curlylint-0.13.0.dist-info/entry_points.txt
curlylint-0.13.0.dist-info/top_level.txt
curlylint-0.13.0.dist-info/RECORD
