Metadata-Version: 2.1
Name: curlylint
Version: 0.13.0
Summary: {{ 🎀}} Experimental HTML templates linting for Jinja, Nunjucks, Django templates, Twig, Liquid
Home-page: https://github.com/thibaudcolas/curlylint
Author: Thibaud Colas
Author-email: thibaudcolas@gmail.com
License: MIT
Keywords: curlylint,linter,linting,jinja,jinja2,django templates,twig,nunjucks,liquid,templates,html
Platform: UNKNOWN
Classifier: Development Status :: 3 - Alpha
Classifier: Environment :: Console
Classifier: Intended Audience :: Developers
Classifier: License :: OSI Approved :: MIT License
Classifier: Topic :: Software Development :: Quality Assurance
Classifier: Typing :: Typed
Classifier: Programming Language :: Python :: 3
Classifier: Programming Language :: Python :: 3 :: Only
Classifier: Programming Language :: Python :: 3.6
Classifier: Programming Language :: Python :: 3.7
Classifier: Programming Language :: Python :: 3.8
Classifier: Programming Language :: Python :: 3.9
Classifier: Programming Language :: Python :: 3.10
Requires-Python: >=3.6
Requires-Dist: parsy (==1.1.0)
Requires-Dist: attrs (>=17.2.0)
Requires-Dist: click (>=6.5)
Requires-Dist: toml (>=0.9.4)
Requires-Dist: pathspec (<1,>=0.6)
Requires-Dist: dataclasses (>=0.6) ; python_version < "3.7"
